{
    "Darien": {
        "is_online": true,
        "username": "Darien26"
    },
    "user69608825...": {
        "is_online": false,
        "username": "user696088256512532480"
    },
    "bigpigboy": {
        "is_online": false,
        "username": "bigpigboy"
    },
    "Knuu": {
        "is_online": false,
        "username": "yungviber"
    },
    "Missalexissx...": {
        "is_online": false,
        "username": "missalexissx"
    },
    "kjrs": {
        "is_online": true,
        "username": "kjrs"
    },
    "Santy": {
        "is_online": false,
        "username": "user720519765482811392"
    },
    "Olav": {
        "is_online": false,
        "username": "Snibbolaien"
    },
    "Rosss5463": {
        "is_online": false,
        "username": "Rosss5463"
    },
    "Jason": {
        "is_online": false,
        "username": "user579386871973421056"
    },
    "Rh": {
        "is_online": false,
        "username": "user674812188875038721"
    },
    "Jim": {
        "is_online": true,
        "username": "MartirasNoor2"
    },
    "Matt": {
        "is_online": false,
        "username": "fe4chd"
    },
    "Disspirado": {
        "is_online": false,
        "username": "user711233234398097409"
    },
    "babyfa24": {
        "is_online": false,
        "username": "babyfa24"
    },
    "Ricoooo": {
        "is_online": false,
        "username": "user688821157478019072"
    },
    "Sprk": {
        "is_online": false,
        "username": "user612824448608772097"
    },
    "Kevin": {
        "is_online": false,
        "username": "KevinFN"
    },
    "Metzy47": {
        "is_online": true,
        "username": "Metzy47"
    },
    "n4thak": {
        "is_online": false,
        "username": "n4thak"
    },
    ".soner": {
        "is_online": false,
        "username": "Bylazo"
    },
    "Manu2.0": {
        "is_online": false,
        "username": "Emmanuel4date"
    },
    "g_kokanis": {
        "is_online": false,
        "username": "g_kokanis"
    },
    "Coady": {
        "is_online": false,
        "username": "user362994396817272832"
    },
    "Andy3522488": {
        "is_online": true,
        "username": "Andy3522488"
    },
    "Miteas": {
        "is_online": false,
        "username": "Miketas"
    },
    "user60574563...": {
        "is_online": true,
        "username": "user605745639774498856"
    },
    "James": {
        "is_online": false,
        "username": "some_random-user3321"
    },
    "Andrés Mauri...": {
        "is_online": false,
        "username": "andresmauricioreyesc"
    },
    "Bart_69": {
        "is_online": true,
        "username": "Bart_69"
    },
    "Steffan": {
        "is_online": false,
        "username": "S1t2f"
    },
    "eskilos": {
        "is_online": false,
        "username": "eskilos"
    },
    "Royal Manage...": {
        "is_online": false,
        "username": "RoyalManagement"
    },
    "Jake D": {
        "is_online": false,
        "username": "Jakedulley"
    },
    "Catt1552": {
        "is_online": false,
        "username": "user642438784754921472"
    },
    "Lennyforfun": {
        "is_online": false,
        "username": "Lennyforfun"
    },
    "Lein": {
        "is_online": true,
        "username": "leinarg"
    },
    "Yuyuyu": {
        "is_online": false,
        "username": "yuyggdyuhbvsd"
    },
    "Gloria99": {
        "is_online": false,
        "username": "user601045592759607296"
    },
    "estevanahern...": {
        "is_online": false,
        "username": "estevanahernandez725"
    },
    "Selmar": {
        "is_online": false,
        "username": "user681682579455221761"
    },
    "gussypal": {
        "is_online": true,
        "username": "gussypal"
    },
    "KattySwitch": {
        "is_online": true,
        "username": "kattyswitch"
    },
    "redhead896": {
        "is_online": false,
        "username": "redhead896"
    },
    "Beefstew117": {
        "is_online": false,
        "username": "Beefstew117"
    },
    "dadiiiiiiii9...": {
        "is_online": false,
        "username": "dadiiiiiiii98"
    },
    "TwixClubChun...": {
        "is_online": false,
        "username": "TwixClubChunky"
    },
    "Sfir2": {
        "is_online": false,
        "username": "Rbv1980"
    },
    "JThorne": {
        "is_online": true,
        "username": "JThorne"
    },
    "Tahirsandhu": {
        "is_online": false,
        "username": "user702286836914991106"
    },
    "user69791358...": {
        "is_online": false,
        "username": "user697913581554900992"
    },
    "citylucky": {
        "is_online": false,
        "username": "citylucky"
    },
    "Ivan_1983": {
        "is_online": true,
        "username": "Ivan_1983"
    },
    "pihkurmees": {
        "is_online": false,
        "username": "pihkurmees"
    },
    "Guillermo": {
        "is_online": false,
        "username": "_guillermo_"
    },
    "Kivo": {
        "is_online": false,
        "username": "user653300257823666176"
    },
    ".Seldy9": {
        "is_online": false,
        "username": "Seldy9"
    },
    "And I am Lib...": {
        "is_online": true,
        "username": "Libor83"
    },
    "Tradammis": {
        "is_online": false,
        "username": "Tradammis"
    },
    "David smith": {
        "is_online": false,
        "username": "user490030690952290304"
    },
    "Fishing dude...": {
        "is_online": false,
        "username": "airsoft950407"
    },
    "joyg123": {
        "is_online": false,
        "username": "joyg123"
    },
    "user61779424...": {
        "is_online": false,
        "username": "user617794243628380160"
    },
    "thedood345": {
        "is_online": true,
        "username": "thedood345"
    },
    "user50460418...": {
        "is_online": false,
        "username": "user504604181294755840"
    },
    "Darrynsis": {
        "is_online": false,
        "username": "Darrynsis"
    },
    "Henny699": {
        "is_online": false,
        "username": "Henny699"
    },
    "Mattyice2117...": {
        "is_online": false,
        "username": "user480819581196185600"
    }
}